[
  {
    "id": "394808f9-cdaa-460e-86df-b1c000b34cbc",
    "title": "iPhone 13 Starlight BATERIE 100% TOP",
    "price": "8 490 Kč",
    "link": "https://mobil.bazos.cz/inzerat/214990884/iphone-13-starlight-baterie-100-top.php",
    "date_posted": "- TOP - [14.3. 2026]",
    "brand": "Apple",
    "ad_type": "nabidka",
    "scraped_at": "2026-03-14T17:40:41.775Z",
    "description": "Nabízím tento nádherný ZÁNOVNÍ plně funkční iPhone 13 kapacity úložiště 128 GB krásné bílé barevné varianty v TOP STAVU, jako nový, s maximální KONDICÍ BATERIE 100% a KOMPLETNÍM novým BALENÍM, prakticky koupíte řádný nový kus se vším všudy, bez obav  ...",
    "location": "Ostrava702 00"
  },
  {
    "id": "6a90bbbf-c4a2-4028-a5fe-0c594b9f3ee8",
    "title": "16 Pro 256 GB, Apple Watch series 8",
    "price": "20 000 Kč",
    "link": "https://mobil.bazos.cz/inzerat/216122472/16-pro-256-gb-apple-watch-series-8.php",
    "date_posted": "- TOP - [14.3. 2026]",
    "brand": "Apple",
    "ad_type": "nabidka",
    "scraped_at": "2026-03-14T17:40:41.785Z",
    "description": "Prodám 16 Pro, jako bonus přidám watchky,\nStav baterie 91 %\nKupuji 17 Pro",
    "location": "Kolín282 01"
  },
  {
    "id": "8aae3a8f-eb10-4777-a93b-766fa2274587",
    "title": "Iphone 16 Pro Max",
    "price": "23 900 Kč",
    "link": "https://mobil.bazos.cz/inzerat/216112788/iphone-16-pro-max.php",
    "date_posted": "- TOP - [14.3. 2026]",
    "brand": "Apple",
    "ad_type": "nabidka",
    "scraped_at": "2026-03-14T17:40:41.792Z",
    "description": "Prodám Iphone 16 Pro Max zlatý.\nIphone je bez jediného škrábance či oděrky.\nStav baterie 93% rok starý.\nJeště v záruce kupovaný v Istyle Olympia Brno.\nMá kryt čoček i sklo na displeji.\n100% stav používání. \nPři rychlém jednaní sleva.",
    "location": "Brno616 00"
  },
  {
    "id": "5df541e1-b062-4fb5-8d25-dc174c4b326b",
    "title": "iPHONE 15 PRO MAX 512 GB TOP STAV - BLACK",
    "price": "16 900 Kč",
    "link": "https://mobil.bazos.cz/inzerat/215377415/iphone-14-pro-max-512-gb.php",
    "date_posted": "- TOP - [14.3. 2026]",
    "brand": "Apple",
    "ad_type": "nabidka",
    "scraped_at": "2026-03-14T17:40:41.801Z",
    "description": "Prodám mobilní telefon iPHONE 15 PRO MAX 512 GB , V perfektním stavu , netknutý stav nového telefonu vhodné také jako dárek. Baterie 95% , funkční bezproblémový barva BLACK , material TITAN . Cena včetně příslušenství + 2x ochranné sklo s aplikatorem ...",
    "location": "Praha 10108 00"
  },
  {
    "id": "2374b3f5-375a-4a0a-b1c2-42d582272d0e",
    "title": "IPhone 15 PRO  128Gb dark blue , top stav",
    "price": "13 499 Kč",
    "link": "https://mobil.bazos.cz/inzerat/215827652/iphone-15-pro-128gb-dark-blue-top-stav.php",
    "date_posted": "- TOP - [14.3. 2026]",
    "brand": "Apple",
    "ad_type": "nabidka",
    "scraped_at": "2026-03-14T17:40:41.807Z",
    "description": "Prodám iPhone 15 Pro 128gb v perfektním stavu, absolutně bez škrábanců. kondice baterie 90%.\nPo odzkoušení dám do továrního nastavení. cena je pevná, nesmlouvám.Opava,Ostrava,Nový Jičín",
    "location": "Opava747 45"
  },
  {
    "id": "90441517-e153-46b4-ba59-2c0d0ffbd1d2",
    "title": "Iphone 16 Pro Max 256GB Black Titanum nový se zárukou",
    "price": "25 000 Kč",
    "link": "https://mobil.bazos.cz/inzerat/215349922/iphone-16-pro-max-256gb-black-titanum-novy-se-zarukou.php",
    "date_posted": "- TOP - [14.3. 2026]",
    "brand": "Apple",
    "ad_type": "nabidka",
    "scraped_at": "2026-03-14T17:40:41.813Z",
    "description": "Prodám nový nerozbalený Iphone 16 Pro Max 256GB Black Titanum se zárukou Apple z české distribuce.",
    "location": "Opava748 01"
  },
  {
    "id": "0a041b74-5984-43fd-8b10-a174b436b99c",
    "title": "Iphone 15 Pro Max 512GB modrý titan",
    "price": "16 500 Kč",
    "link": "https://mobil.bazos.cz/inzerat/215483933/iphone-15-pro-max-512gb-modry-titan.php",
    "date_posted": "- TOP - [14.3. 2026]",
    "brand": "Apple",
    "ad_type": "nabidka",
    "scraped_at": "2026-03-14T17:40:41.818Z",
    "description": "Iphone 15 Pro Max 512GB modrý titan v perfektním stavu bez jediného, nošen v obalu bez škrábance včetně příslušenství.\n\nStav Baterie:  92%, výdrž 2 dny\n\nStáří 2 roky Koupeno v ČR v ceně 2 x obal s magsafe, 2 x nové 3D ochranné sklo Premium.\nZáruka na ...",
    "location": "Opava748 01"
  },
  {
    "id": "8b5e33f3-0898-41ce-a5c8-4069f1416047",
    "title": "APPLE IPHONE 13 PRO 128 GB ŠEDÝ,12 MĚS.ZÁRUKA,JAKO NOVÝ",
    "price": "8 990 Kč",
    "link": "https://mobil.bazos.cz/inzerat/215737959/apple-iphone-13-pro-128-gb-sedy12-meszarukajako-novy.php",
    "date_posted": "- TOP - [14.3. 2026]",
    "brand": "Apple",
    "ad_type": "nabidka",
    "scraped_at": "2026-03-14T17:40:41.826Z",
    "description": "Prodám iPhone 13 PRO 128 GB, plně funkční, neblokovaný, v továrním nastavení\n\nTELEFON JE V KRÁSNÉM STAVU, JAKO NOVÝ, KONDICE BATERIE 92%\n\nVčetně USB(A) kabelu\n\n\nMožnost dokoupení tvrzeného skla, obalu nebo USB(A) adaptéru\n\nSERIÓZNÍ JEDNÁNÍ V ...",
    "location": "Praha 9190 00"
  },
  {
    "id": "834bf42d-b64a-480c-a423-0cc44fe43f52",
    "title": "iPhone 16 Pro 256Gb Desert Titanium",
    "price": "18 000 Kč",
    "link": "https://mobil.bazos.cz/inzerat/216209579/iphone-16-pro-256gb-desert-titanium.php",
    "date_posted": "- TOP - [14.3. 2026]",
    "brand": "Apple",
    "ad_type": "nabidka",
    "scraped_at": "2026-03-14T17:40:41.835Z",
    "description": "Prodám iPhone 16 Pro 256Gb Desert Titanium ve vynikajícím stavu bez jediného škrábnutí. Telefon zakoupený před rokem. Důvod prodeje výměna za novější. Komplet balení včetně nabíjecího kabelů.",
    "location": "Nymburk289 24"
  },
  {
    "id": "322fcf41-f641-49a2-9426-9534391dbfcf",
    "title": "iPhone 14 Pro Max",
    "price": "10 700 Kč",
    "link": "https://mobil.bazos.cz/inzerat/216198022/apple-iphone-14-pro-max.php",
    "date_posted": "- TOP - [14.3. 2026]",
    "brand": "Apple",
    "ad_type": "nabidka",
    "scraped_at": "2026-03-14T17:40:41.841Z",
    "description": "Plně funkční telefon. Nikdy neopravovaný. Paměť 256gb, baterie 87%, kompletní balení v original krabičce. Displej i zadní kryt absolutně bez škrábanců a jiných poškození. Boky telefonu trochu fleků od krytu. Osobní převzetí v Kroměříži a okolí. Jinak ...",
    "location": "Kroměříž767 01"
  },
  {
    "id": "012cc0df-13a1-4ebe-a434-84343c2f9e89",
    "title": "iPhone 13 PRO 128gb Sierra Blue",
    "price": "8 490 Kč",
    "link": "https://mobil.bazos.cz/inzerat/216198466/iphone-13-pro-128gb-sierra-blue.php",
    "date_posted": "- TOP - [14.3. 2026]",
    "brand": "Apple",
    "ad_type": "nabidka",
    "scraped_at": "2026-03-14T17:40:41.848Z",
    "description": "Prodam iPhone 13 Pro 128gb \nTelefon je v dobrém stavu, icloud je odhlášen a připraven pro noveho majitele.\n Možnost osobního odběru okolí Třince Popř. po domluvě není problém zaslat poštou (Požaduji platbu předem 200,- za poštovné)",
    "location": "Frýdek - Místek739 61"
  },
  {
    "id": "5236808c-f3a3-49ec-a88d-d446ee4a7e95",
    "title": "iPhone 15 Pro 128gb Blue Titanium",
    "price": "13 490 Kč",
    "link": "https://mobil.bazos.cz/inzerat/216033743/iphone-15-pro-128gb-blue-titanium.php",
    "date_posted": "- TOP - [14.3. 2026]",
    "brand": "Apple",
    "ad_type": "nabidka",
    "scraped_at": "2026-03-14T17:40:41.860Z",
    "description": "iPhone 15 pro 128gb Telefon je v hezkém stavu, icloud je odhlášen a připraven pro noveho majitele. Možnost osobního odběru okolí Třince. Popř. po domluvě není problém zaslat poštou (Požaduji platbu předem 200,- za poštovné)",
    "location": "Frýdek - Místek739 61"
  },
  {
    "id": "aba2a41f-b703-483e-b54f-1af05d00fe05",
    "title": "iPhone 14 Pro max 128gb Deep purple",
    "price": "11 490 Kč",
    "link": "https://mobil.bazos.cz/inzerat/216198592/iphone-14-pro-max-128gb-deep-purple.php",
    "date_posted": "- TOP - [14.3. 2026]",
    "brand": "Apple",
    "ad_type": "nabidka",
    "scraped_at": "2026-03-14T17:40:41.865Z",
    "description": "iPhone 14 pro Max 128gb Deep purple\nTelefon je v hezkém stavu, icloud je odhlášen a připraven pro noveho majitele.\nMožnost osobního odběru okolí Třince. Popř. po domluvě není problém zaslat poštou (Požaduji platbu předem 200,- za poštovné)",
    "location": "Frýdek - Místek739 61"
  },
  {
    "id": "87fa6e7a-c5bd-4fbe-a2d0-64ab53e60eec",
    "title": "iPhone 14 pro 128GB",
    "price": "9 600 Kč",
    "link": "https://mobil.bazos.cz/inzerat/216156488/iphone-14-pro-128gb.php",
    "date_posted": "- TOP - [14.3. 2026]",
    "brand": "Apple",
    "ad_type": "nabidka",
    "scraped_at": "2026-03-14T17:40:41.873Z",
    "description": "Nabízím iPhone 14 pro 128 GB, kupovaný 5/ 2023 jako nový, 1 majitel, nový displej , v balení telefon, krabička, nabíječka, 1 kryt. Stav baterie 85%,",
    "location": "Karviná734 01"
  },
  {
    "id": "096c884e-4286-411b-a841-c26b07bd21c2",
    "title": "IPhone 12, 64 GB, stav baterie 81%, v super stavu",
    "price": "3 500 Kč",
    "link": "https://mobil.bazos.cz/inzerat/215942730/iphone-12-64-gb-stav-baterie-81-v-super-stavu.php",
    "date_posted": "- TOP - [14.3. 2026]",
    "brand": "Apple",
    "ad_type": "nabidka",
    "scraped_at": "2026-03-14T17:40:41.883Z",
    "description": "Prodám iPhone 12 s 6,1\" OLED displejem (Super Retina XDR). Telefon je plně funkční, odhlášený z iCloudu a připravený pro nového majitele.\n\nParametry:\n\ndisplej 6,1\" Super Retina XDR\núložiště 64 GB\nFace ID\nduální fotoaparát 12 MP (wide + ultra-w ...",
    "location": "Praha 3130 00"
  },
  {
    "id": "2c6a636e-4a62-4d48-af2e-2b0c2d3dad0c",
    "title": "APPLE IPHONE 17 256 GB ČERNÝ,2 ROKY ZÁRUKA,NOVÝ,NEROZBALENÝ",
    "price": "19 990 Kč",
    "link": "https://mobil.bazos.cz/inzerat/216083543/apple-iphone-17-256-gb-cerny2-roky-zarukanovynerozbaleny.php",
    "date_posted": "- TOP - [14.3. 2026]",
    "brand": "Apple",
    "ad_type": "nabidka",
    "scraped_at": "2026-03-14T17:40:41.891Z",
    "description": "Prodám nový iPhone 17 256 GB\n\nTELEFON JE NOVÝ, NEPOUŽÍVANÝ, NEAKTIVOVANÝ\n\nTELEFON JE V ORIGINÁLNÍ NEOTEVŘENÉ KRABIČCE, STANDARDNÍ ZÁRUKA 2 ROKY\n\nPŘI NÁKUPU NA IČO NELZE ODEČÍST DPH\n\nSTANDARDNÍ VERZE NA FYZICKOU SIM KARTU\n\n\nSERIÓZNÍ JEDNÁNÍ ...",
    "location": "Praha 9190 00"
  },
  {
    "id": "836ee48b-2cc4-40c9-9ca6-4d82c32a63b9",
    "title": "iPhone 15 Pro Max 256GB - TOP stav, jako nový",
    "price": "14 500 Kč",
    "link": "https://mobil.bazos.cz/inzerat/216079794/iphone-15-pro-max-256gb-top-stav-jako-novy.php",
    "date_posted": "- TOP - [14.3. 2026]",
    "brand": "Apple",
    "ad_type": "nabidka",
    "scraped_at": "2026-03-14T17:40:41.898Z",
    "description": "Prodám svůj iPhone z důvodu přechodu na nový 17 pro Max.\n\nPlně funkční, nikdy nebyl opravován. \nBarva: přírodní Titan\nUložiště: 256GB\nKondice baterie 85% \nČeská distribuce - koupen v iWant\nVnější stav 10/10, od začátku byl v pouzdře s ochranným sklem ...",
    "location": "Praha 1110 00"
  },
  {
    "id": "10b69bec-f354-4bfc-8888-d772596f967b",
    "title": "iPhone 13 Pro 128GB Gold",
    "price": "7 500 Kč",
    "link": "https://mobil.bazos.cz/inzerat/216074880/iphone-13-pro-128gb-gold.php",
    "date_posted": "- TOP - [14.3. 2026]",
    "brand": "Apple",
    "ad_type": "nabidka",
    "scraped_at": "2026-03-14T17:40:41.903Z",
    "description": "Velmi pěkný stav. \nPoužívaný necelé 4 roky.\nBaterie 83%.\n\nOsobní předání nebo zaslání PPL/Zásilkovna",
    "location": "Liberec460 05"
  },
  {
    "id": "814f77fd-3e7b-4c98-ab7e-5049f15ff731",
    "title": "ZÁNOVNÍ APPLE IPHONE 16 PRO MAX 256GB ZLATÝ,100% BATERIE",
    "price": "19 999 Kč",
    "link": "https://mobil.bazos.cz/inzerat/216049600/zanovni-apple-iphone-16-pro-max-256gb-zlaty100-baterie.php",
    "date_posted": "- TOP - [14.3. 2026]",
    "brand": "Apple",
    "ad_type": "nabidka",
    "scraped_at": "2026-03-14T17:40:41.909Z",
    "description": "Prodám zánovní Apple iPhone 16 Pro Max s kapacitou 256 GB v barvě pouštní titan. Telefon je plně funkční, neblokovaný. Telefon je určen pro evropský trh, tudíž na fyzickou SIM!!\n\nBaterie: 100%\n\nSoučástí prodeje je telefon a USB kabel.\nKontakt: + ...",
    "location": "Praha 8180 00"
  },
  {
    "id": "58672db2-fd13-47a7-9172-3d1f52f6d168",
    "title": "APPLE IPHONE 15 PRO 128GB ČERNÝ TITAN, ZÁRUKA, 100% BATERIE",
    "price": "14 499 Kč",
    "link": "https://mobil.bazos.cz/inzerat/216049545/zanovni-apple-iphone-16-pro-512gb-cerny-100-baterie.php",
    "date_posted": "- TOP - [14.3. 2026]",
    "brand": "Apple",
    "ad_type": "nabidka",
    "scraped_at": "2026-03-14T17:40:41.916Z",
    "description": "Prodám Apple iPhone 15 Pro s kapacitou 128 GB v elegantní barvě černý titan. Telefon je plně funkční, neblokovaný a ve velmi pěkném stavu. Telefon je určen pro evropský trh, tudíž na fyzickou SIM!!\n\nBaterie: 100%\n\nSoučástí prodeje je telefon a US ...",
    "location": "Praha 8180 00"
  },
  {
    "id": "437f18fe-c3fd-4875-a4f1-58d3b1a07811",
    "title": "APPLE IPHONE 14 PRO 128GB ČERNÝ, ZÁRUKA, 100% BATERIE",
    "price": "10 499 Kč",
    "link": "https://mobil.bazos.cz/inzerat/216049364/apple-iphone-14-pro-128gb-cerny-zaruka-100-baterie.php",
    "date_posted": "- TOP - [14.3. 2026]",
    "brand": "Apple",
    "ad_type": "nabidka",
    "scraped_at": "2026-03-14T17:40:45.032Z",
    "description": "Prodám Apple iPhone 14 Pro s kapacitou 128 GB v černé barvě. Telefon je plně funkční, neblokovaný, nese známky používání.\n\nBaterie: 100%\n\nSoučástí prodeje je telefon a USB kabel.\nKontakt: +420739993334\n\nCena je pevně stanovená a k telefonu pos ...",
    "location": "Praha 8180 00"
  },
  {
    "id": "df7edff7-93cf-4cff-8a73-43518f818466",
    "title": "APPLE IPHONE 13 PRO MAX 128GB MODRÝ, ZÁRUKA",
    "price": "9 499 Kč",
    "link": "https://mobil.bazos.cz/inzerat/216049288/apple-iphone-13-pro-max-128gb-modry-zaruka.php",
    "date_posted": "- TOP - [14.3. 2026]",
    "brand": "Apple",
    "ad_type": "nabidka",
    "scraped_at": "2026-03-14T17:40:45.042Z",
    "description": "Prodám Apple iPhone 13 Pro Max s kapacitou 128 GB v modré barvě. Telefon je plně funkční, neblokovaný, nese známky používání.\n\nSoučástí prodeje je telefon a USB kabel.\nKontakt: +420739993334\n\nCena je pevně stanovená a k telefonu poskytují měsíčn ...",
    "location": "Praha 8180 00"
  },
  {
    "id": "8eb88422-b758-4fda-8522-0ab794d59495",
    "title": "APPLE IPHONE 13 128GB ČERNÝ, ZÁRUKA, 100% BATERIE",
    "price": "5 999 Kč",
    "link": "https://mobil.bazos.cz/inzerat/216049194/apple-iphone-13-128gb-cerny-zaruka-100-baterie.php",
    "date_posted": "- TOP - [14.3. 2026]",
    "brand": "Apple",
    "ad_type": "nabidka",
    "scraped_at": "2026-03-14T17:40:45.060Z",
    "description": "Prodám Apple iPhone 13 s kapacitou 128 GB v černé barvě. Telefon je plně funkční, neblokovaný, nese známky používání.\n\nBaterie: 100%\n\nSoučástí prodeje je telefon a USB kabel.\nKontakt: +420739993334\n\nCena je pevně stanovená a k telefonu poskytu ...",
    "location": "Praha 8180 00"
  },
  {
    "id": "c71b8310-ee21-4867-84fb-3c3b59708acc",
    "title": "APPLE IPHONE 12 64GB BÍLÝ, ZÁRUKA, 100% BATERIE",
    "price": "4 499 Kč",
    "link": "https://mobil.bazos.cz/inzerat/216049108/apple-iphone-12-64gb-bily-zaruka-100-baterie.php",
    "date_posted": "- TOP - [14.3. 2026]",
    "brand": "Apple",
    "ad_type": "nabidka",
    "scraped_at": "2026-03-14T17:40:45.069Z",
    "description": "Prodám Apple iPhone 12 s kapacitou 64 GB v bílé barvě. Telefon je plně funkční, neblokovaný.\n\nBaterie: 100%\n\nSoučástí prodeje je telefon a USB kabel.\nKontakt: +420739993334\n\n\nCena je pevně stanovená a k telefonu poskytují měsíční záruku. Před ...",
    "location": "Praha 8180 00"
  },
  {
    "id": "f80d538e-445d-4951-834e-a796e5029cad",
    "title": "APPLE IPHONE XR  64GB BÍLÝ, ZÁRUKA, 100% BATERIE",
    "price": "2 799 Kč",
    "link": "https://mobil.bazos.cz/inzerat/216048987/apple-iphone-xr-64gb-bily-zaruka-100-baterie.php",
    "date_posted": "- TOP - [14.3. 2026]",
    "brand": "Apple",
    "ad_type": "nabidka",
    "scraped_at": "2026-03-14T17:40:45.077Z",
    "description": "Prodám Apple iPhone XR s kapacitou 64 GB v bílé barvě. Telefon je plně funkční, neblokovaný\n\nNová baterie: 100%\n\nSoučástí prodeje je telefon a USB kabel.\nKontakt: +420739993334\n\n\nCena je pevně stanovená a k telefonu poskytují měsíční záruku.  ...",
    "location": "Praha 8180 00"
  },
  {
    "id": "67553f64-9ea9-4ca9-9607-a87f07ee9f49",
    "title": "APPLE IPHONE SE2 2020 64GB ČERNÝ, ZÁRUKA, 100% BATERIE",
    "price": "2 799 Kč",
    "link": "https://mobil.bazos.cz/inzerat/216048783/apple-iphone-se2-2020-64gb-cerny-zaruka-100-baterie.php",
    "date_posted": "- TOP - [14.3. 2026]",
    "brand": "Apple",
    "ad_type": "nabidka",
    "scraped_at": "2026-03-14T17:40:45.084Z",
    "description": "Prodám Apple iPhone SE 2020 s kapacitou 64 GB v černé barvě. Telefon je plně funkční, neblokovaný\n\nBaterie: 100%\n\nSoučástí prodeje je telefon a USB kabel.\nKontakt: +420739993334\n\n\nCena je pevně stanovená a k telefonu poskytují měsíční záruku. ...",
    "location": "Praha 8180 00"
  },
  {
    "id": "0a6a3cf7-0ae9-4e2a-bdc8-d125d7c69fe7",
    "title": "Apple iPhone 17 Pro Max 256 GB Deep Blue – nový, nerozbalený",
    "price": "31 500 Kč",
    "link": "https://mobil.bazos.cz/inzerat/215831972/apple-iphone-17-pro-max-256-gb-deep-blue-novy-nerozbaleny.php",
    "date_posted": "- TOP - [14.3. 2026]",
    "brand": "Apple",
    "ad_type": "nabidka",
    "scraped_at": "2026-03-14T17:40:45.090Z",
    "description": "Prodám úplně nový Apple iPhone 17 Pro Max 256 GB v barvě Deep Blue. Telefon je zabalený v originální fólii, nikdy nepoužitý.\n\t•\tKapacita: 256 GB\n\t•\tBarva: Deep Blue\n\t•\tStav: nový, nerozbalený\n\t•\tZáruka 2 roky, doklad samozřejmostí \n\t•\tProdejce:  ...",
    "location": "Praha 9190 00"
  },
  {
    "id": "a74032f3-9d26-418b-bd64-49e01708fdfe",
    "title": "APPLE IPHONE 15 128 GB ZELENÝ,12 MĚSÍCŮ ZÁRUKA,JAKO NOVÝ",
    "price": "10 990 Kč",
    "link": "https://mobil.bazos.cz/inzerat/215823847/apple-iphone-15-128-gb-modry12-mesicu-zarukajako-novy.php",
    "date_posted": "- TOP - [14.3. 2026]",
    "brand": "Apple",
    "ad_type": "nabidka",
    "scraped_at": "2026-03-14T17:40:45.098Z",
    "description": "Prodám iPhone 15 128 GB, plně funkční, neblokovaný, v továrním nastavení\n\nTELEFON JE V KRÁSNÉM STAVU, JAKO NOVÝ, KONDICE BATERIE 87%\n\nVčetně USB(A) kabelu\n\n\nMožnost dokoupení tvrzeného skla, obalu nebo USB(A) adaptéru\n\nSERIÓZNÍ JEDNÁNÍ VIZ.  ...",
    "location": "Praha 9190 00"
  },
  {
    "id": "e29aceed-e70b-4c82-b313-1ee2dc99de84",
    "title": "iPhone 13 Pro 512 GB vesmírně šedý",
    "price": "6 990 Kč",
    "link": "https://mobil.bazos.cz/inzerat/214797887/iphone-13-pro-512-gb-tm-sedy.php",
    "date_posted": "- TOP - [14.3. 2026]",
    "brand": "Apple",
    "ad_type": "nabidka",
    "scraped_at": "2026-03-14T17:40:45.104Z",
    "description": "Po 2 letech spokojeného používání posílám do světa tento iPhone 13 Pro 512 GB. \n- výborný všestranný telefon \n- funkčně naprosto v pořádku, telefonu nic není\n- zvýhodněná cena oproti trhu a podobným telefonům kvůli vlásečnicích na zadním skle, viz ...",
    "location": "Praha 10111 01"
  },
  {
    "id": "014f69d2-997d-4937-a584-434b1fc8c78b",
    "title": "iPhone 17 512 GB 🍏 jako nový | záruka",
    "price": "22 999 Kč",
    "link": "https://mobil.bazos.cz/inzerat/215975489/iphone-17-512-gb-jako-novy-zaruka.php",
    "date_posted": "- TOP - [14.3. 2026]",
    "brand": "Apple",
    "ad_type": "nabidka",
    "scraped_at": "2026-03-14T17:40:45.112Z",
    "description": "Prodám tento iphone 17 512 GB zelený ve výborném stavu. \nJako nový. Lehce používány.\nBaterie: 100% \nZáruka 2 roky u mobil pohotovosti \nPřidám k telefonu 2 prémiové kryty s magsafe na telefon (jejich cena byla 1500 Kč)\nOchranné sklíčko již nalepené.\nO ...",
    "location": "Praha 10108 00"
  },
  {
    "id": "0551497d-1ca8-4616-9ecf-97aca4f9a2d5",
    "title": "Apple iPhone 17 Pro 256GB - stříbrný",
    "price": "27 990 Kč",
    "link": "https://mobil.bazos.cz/inzerat/215433411/apple-iphone-17-pro-256gb-stribrny.php",
    "date_posted": "- TOP - [14.3. 2026]",
    "brand": "Apple",
    "ad_type": "nabidka",
    "scraped_at": "2026-03-14T17:40:45.117Z",
    "description": "Prodám Apple iPhone 17 Pro 256GB. \n\nZáruka u T-Mobile.",
    "location": "Ostrava725 25"
  },
  {
    "id": "07a0c5cc-8803-4540-99e6-40e10fa54c94",
    "title": "Apple iPhone 17 512gb šalvějově zelená",
    "price": "22 500 Kč",
    "link": "https://mobil.bazos.cz/inzerat/215660223/apple-iphone-17-512gb-salvejove-zelena.php",
    "date_posted": "- TOP - [14.3. 2026]",
    "brand": "Apple",
    "ad_type": "nabidka",
    "scraped_at": "2026-03-14T17:40:45.123Z",
    "description": "Prodám nový Apple iPhone 17 512GB šalvějově zelená. Telefon je nový z O2 distribuce.",
    "location": "Děčín405 02"
  },
  {
    "id": "4ed20794-cfe7-49e9-bacf-57f06b5c35c7",
    "title": "Apple Iphone 16e  512GB",
    "price": "10 700 Kč",
    "link": "https://mobil.bazos.cz/inzerat/216203961/apple-iphone-1e-bila-barva-512gb.php",
    "date_posted": "- TOP - [14.3. 2026]",
    "brand": "Apple",
    "ad_type": "nabidka",
    "scraped_at": "2026-03-14T17:40:45.129Z",
    "description": "Vyměním nebo prodám za následující telefony...Samsung S24FE (váš doplatek dle dohody), Samsung A56 256GB verze (váš doplatek dle dohody) ,  Xiaomi redmi note 15 pro neb o pro +(váš doplatek dle dohody), Samsung S24 (váš doplatek dle dohody), Xiaomi 1 ...",
    "location": "Praha 4142 00"
  },
  {
    "id": "4aa1a3f1-d1e3-41dc-b52e-c4cf0de92acc",
    "title": "Iphone AIR - 256gb",
    "price": "19 000 Kč",
    "link": "https://mobil.bazos.cz/inzerat/216199693/iphone-air-256gb.php",
    "date_posted": "- TOP - [14.3. 2026]",
    "brand": "Apple",
    "ad_type": "nabidka",
    "scraped_at": "2026-03-14T17:40:45.134Z",
    "description": "Prodám iphone air kupovaný 24.2.2026, vše v pohodě, jedná se o telefon starý 14 dní zakoupený v planeu. Tudíž je i 2 roky v záruce. Na displeji nalepeno ochrané sklo",
    "location": "Plzeň301 00"
  },
  {
    "id": "4d3f3bb1-dd28-4bd7-b8d0-ae7576590608",
    "title": "IPhone 13 pro max 128 gb",
    "price": "8 400 Kč",
    "link": "https://mobil.bazos.cz/inzerat/216132720/iphone-pro-max-128-gb.php",
    "date_posted": "- TOP - [14.3. 2026]",
    "brand": "Apple",
    "ad_type": "nabidka",
    "scraped_at": "2026-03-14T17:40:45.141Z",
    "description": "Telefon prakticky ve stavu nového + dva kryty.",
    "location": "Kutná Hora286 01"
  },
  {
    "id": "b43b3ef0-e512-4c05-a630-b5e0c9d68e7a",
    "title": "iPhone 13 Pro max 256GB",
    "price": "8 500 Kč",
    "link": "https://mobil.bazos.cz/inzerat/216199026/iphone-13-pro-max-256gb.php",
    "date_posted": "- TOP - [14.3. 2026]",
    "brand": "Apple",
    "ad_type": "nabidka",
    "scraped_at": "2026-03-14T17:40:45.148Z",
    "description": "Predám iPhone 13 Pro max 256gb\nMa malé známky používania pridám k nemu zdarma aj obal quadlock \n\nPraha osobný odber",
    "location": "Praha 8186 00"
  },
  {
    "id": "67fb738b-7d1b-45b3-884a-5f079d85dafe",
    "title": "IPHONE 17 PRO MAX 256GB ORANŽOVÝ NOVÝ 2 ROKY CZ ZÁRUKA",
    "price": "28 500 Kč",
    "link": "https://mobil.bazos.cz/inzerat/216197763/iphone-17-pro-max-256gb-oranzovy-novy-2-roky-cz-zaruka.php",
    "date_posted": "- TOP - [14.3. 2026]",
    "brand": "Apple",
    "ad_type": "nabidka",
    "scraped_at": "2026-03-14T17:40:45.153Z",
    "description": "Telefon je nový, nerozbalený, koupen u CZ distribuce SIM+ESIM. 2 roky záruka + rozšířená záruka na okamžitou výměnu. Záruční list předám při prodeji novému majiteli. Nejlépe osobní předání v Brně nebo v okolí. Při rychlém a slušném jednání možná doho ...",
    "location": "Brno602 00"
  },
  {
    "id": "d91a04ea-2c4f-4b43-87c9-c599673eb856",
    "title": "IPhone 16e 8/128 gb černý prasklé tvrzené sklo",
    "price": "9 000 Kč",
    "link": "https://mobil.bazos.cz/inzerat/216193608/iphone-16e-81128-gb-cerny.php",
    "date_posted": "- TOP - [14.3. 2026]",
    "brand": "Apple",
    "ad_type": "nabidka",
    "scraped_at": "2026-03-14T17:40:45.159Z",
    "description": "Prasklé jen tvrzené sklo \nTop stav plně funkční bez poškození",
    "location": "Sokolov357 01"
  },
  {
    "id": "e29d956c-a9b9-471c-88e0-708024cab99c",
    "title": "iPhone 15 128GB – TOP STAV, 99% baterie, ZÁRUKA do 06/2027)",
    "price": "12 990 Kč",
    "link": "https://mobil.bazos.cz/inzerat/215924342/iphone-15-128-gb-top-stav.php",
    "date_posted": "- TOP - [14.3. 2026]",
    "brand": "Apple",
    "ad_type": "nabidka",
    "scraped_at": "2026-03-14T17:40:45.164Z",
    "description": "Prodám iPhone 15 128GB v perfektním stavu. Telefon je prakticky jako nový – od začátku nošen v pouzdře a s ochranným sklem, takže je bez škrábanců a bez poškození.\n🔋 Kondice baterie: 99 %\n🔄 Počet cyklů: 116\n🧾 Záruka do 06/2027 (Alza – mohu doložit do ...",
    "location": "Praha 1110 00"
  },
  {
    "id": "72a703aa-3a69-4d21-b84d-0482c93356e3",
    "title": "Apple iPhone 14 128GB, příslušenství, 5990Kč",
    "price": "5 990 Kč",
    "link": "https://mobil.bazos.cz/inzerat/216160678/apple-iphone-14-128gb-prislusenstvi-6200kc.php",
    "date_posted": "- TOP - [14.3. 2026]",
    "brand": "Apple",
    "ad_type": "nabidka",
    "scraped_at": "2026-03-14T17:40:45.169Z",
    "description": "K prodeji nabízím mobilní telefon Apple iPhone 14 128GB. Stav telefonu viz foto. Je plně funkční, bez závad. Účty odhlášené, připraven pro nového uživatele. K prodeji s krabičkou, nabíječkou a datovým kabelem. Osobní předání v Praze nebo zaslání (Bal ...",
    "location": "Praha 10102 00"
  },
  {
    "id": "20bed60e-00bb-4a6c-a729-55f887635e37",
    "title": "Apple iPhone 12 Pro 128GB, příslušenství, 4200Kč",
    "price": "4 200 Kč",
    "link": "https://mobil.bazos.cz/inzerat/216171080/apple-iphone-12-128gb-prislusenstvi-3500kc.php",
    "date_posted": "- TOP - [14.3. 2026]",
    "brand": "Apple",
    "ad_type": "nabidka",
    "scraped_at": "2026-03-14T17:40:46.754Z",
    "description": "K prodeji nabízím mobilní telefon Apple iPhone 12 Pro 128GB. Stav telefonu viz foto. Je plně funkční, bez závad. Účty odhlášené, připraven pro nového uživatele. K prodeji s krabičkou, nabíječkou a datovým kabelem. Osobní předání v Praze nebo zaslání  ...",
    "location": "Praha 10102 00"
  },
  {
    "id": "ae101285-e363-461f-970c-ff89ff182b57",
    "title": "Apple iPhone 12 mini 128GB, příslušenství, 2800Kč",
    "price": "2 800 Kč",
    "link": "https://mobil.bazos.cz/inzerat/216172538/apple-iphone-12-mini-128gb-prislusenstvi-2800kc.php",
    "date_posted": "- TOP - [14.3. 2026]",
    "brand": "Apple",
    "ad_type": "nabidka",
    "scraped_at": "2026-03-14T17:40:46.764Z",
    "description": "K prodeji nabízím mobilní telefon Apple iPhone 12 mini 128GB. Stav telefonu viz foto. Je plně funkční, bez závad. Účty odhlášené, připraven pro nového uživatele. K prodeji s nabíječkou a datovým kabelem. Osobní předání v Praze nebo zaslání (Balíkovna ...",
    "location": "Praha 10102 00"
  },
  {
    "id": "0c2e88d5-7501-4ade-8a9f-ef941366601e",
    "title": "Apple iPhone 16e 128GB bílý",
    "price": "10 750 Kč",
    "link": "https://mobil.bazos.cz/inzerat/216169650/apple-iphone-16e-128gb-bily.php",
    "date_posted": "- TOP - [14.3. 2026]",
    "brand": "Apple",
    "ad_type": "nabidka",
    "scraped_at": "2026-03-14T17:40:46.776Z",
    "description": "Prodám 3 týdny používaný Apple iPhone 16e 128GB v bílé barvě. Zakoupený 5.12.2025 u Vodafone. Stav nového zboží. Nevhodný dárek.",
    "location": "Svitavy568 02"
  },
  {
    "id": "3e50cb58-cbd1-4c18-8c62-6bcaa443226f",
    "title": "iPhone 15 Pro 256GB černý, bez škrábance, rok záruka",
    "price": "14 500 Kč",
    "link": "https://mobil.bazos.cz/inzerat/216085367/iphone-15-pro-256gb-cerny-bez-skrabance-rok-zaruka.php",
    "date_posted": "- TOP - [14.3. 2026]",
    "brand": "Apple",
    "ad_type": "nabidka",
    "scraped_at": "2026-03-14T17:40:46.797Z",
    "description": "Prodám plně funkční iPhone ve výborném stavu. Prošel kontrolou a je připraven k okamžitému používání. Vše je možné před zakoupením vyzkoušet.\n\n- Záruka 12 měsíců\n- Všechny součástky jsou original, nebyl opravovaný\n- verze na eSIM\n- Odhlášený od iClou ...",
    "location": "Praha 2120 00"
  },
  {
    "id": "9bc28bfc-8c0c-4671-9e81-434dca414606",
    "title": "iPhone 15 Pro 128GB, 100% baterie, bez škrábance, záruka",
    "price": "13 900 Kč",
    "link": "https://mobil.bazos.cz/inzerat/216119938/iphone-15-pro-128gb-100-baterie-bez-skrabance-zaruka.php",
    "date_posted": "- TOP - [14.3. 2026]",
    "brand": "Apple",
    "ad_type": "nabidka",
    "scraped_at": "2026-03-14T17:40:46.805Z",
    "description": "Prodám plně funkční iPhone ve výborném stavu. Prošel kontrolou a je připraven k okamžitému používání. Vše je možné před zakoupením vyzkoušet.\n\n- Záruka 12 měsíců\n- Všechny součástky jsou original\n- verze na eSIM\n- Odhlášený od iCloudu\n- Dostanete fak ...",
    "location": "Praha 2120 00"
  },
  {
    "id": "dd64aeb9-aa09-4293-bc63-5b261869f4cc",
    "title": "iPhone 13 Pro 128GB zlatý, bez škrábance, rok záruka",
    "price": "7 500 Kč",
    "link": "https://mobil.bazos.cz/inzerat/216120181/iphone-13-pro-128gb-zlaty-bez-skrabance-rok-zaruka.php",
    "date_posted": "- TOP - [14.3. 2026]",
    "brand": "Apple",
    "ad_type": "nabidka",
    "scraped_at": "2026-03-14T17:40:46.811Z",
    "description": "Prodám plně funkční iPhone ve výborném stavu. Prošel kontrolou a je připraven k okamžitému používání. Vše je možné před zakoupením vyzkoušet.\n\n- Záruka 12 měsíců\n- Odhlášený od iCloudu\n- Dostanete fakturu\n- Možnost osobního předání nebo zaslání pošto ...",
    "location": "Praha 2120 00"
  },
  {
    "id": "108227ba-3659-4e6b-b7d1-78e3da22d07f",
    "title": "iPhone 13 Pro 128GB šedý, 100% baterie, rok záruka",
    "price": "7 500 Kč",
    "link": "https://mobil.bazos.cz/inzerat/216120324/iphone-13-pro-128gb-sedy-100-baterie-rok-zaruka.php",
    "date_posted": "- TOP - [14.3. 2026]",
    "brand": "Apple",
    "ad_type": "nabidka",
    "scraped_at": "2026-03-14T17:40:46.817Z",
    "description": "Prodám plně funkční iPhone ve výborném stavu. Prošel kontrolou a je připraven k okamžitému používání. Vše je možné před zakoupením vyzkoušet.\n\n- Záruka 12 měsíců\n- 100% kondice baterie\n- Odhlášený od iCloudu\n- Dostanete fakturu\n- Možnost osobního pře ...",
    "location": "Praha 2120 00"
  },
  {
    "id": "9f36d40d-92fb-4c78-ad5a-2a0bb4960aa7",
    "title": "iPhone 13 Pro 128GB modrý, pěkný stav, 12 měsíců záruka",
    "price": "6 900 Kč",
    "link": "https://mobil.bazos.cz/inzerat/216120356/iphone-13-pro-128gb-modry-pekny-stav-12-mesicu-zaruka.php",
    "date_posted": "- TOP - [14.3. 2026]",
    "brand": "Apple",
    "ad_type": "nabidka",
    "scraped_at": "2026-03-14T17:40:46.845Z",
    "description": "Prodám plně funkční iPhone v dobrém stavu. Prošel kontrolou a je připraven k okamžitému používání. Vše je možné před zakoupením vyzkoušet.\n\n- Záruka 12 měsíců\n- Odhlášený od iCloudu\n- Dostanete fakturu\n- Možnost osobního předání nebo zaslání poštou n ...",
    "location": "Praha 2120 00"
  },
  {
    "id": "ef57e7a6-f23a-41dc-bdf2-e1ebc58f1e84",
    "title": "iPhone 13 Pro 128GB modrý, pěkný stav, rok záruka",
    "price": "7 500 Kč",
    "link": "https://mobil.bazos.cz/inzerat/216120394/iphone-13-pro-128gb-modry-pekny-stav-rok-zaruka.php",
    "date_posted": "- TOP - [14.3. 2026]",
    "brand": "Apple",
    "ad_type": "nabidka",
    "scraped_at": "2026-03-14T17:40:46.851Z",
    "description": "Prodám plně funkční iPhone ve výborném stavu. Prošel kontrolou a je připraven k okamžitému používání. Vše je možné před zakoupením vyzkoušet.\n\n- Záruka 12 měsíců\n- Odhlášený od iCloudu\n- Dostanete fakturu\n- Možnost osobního předání nebo zaslání pošto ...",
    "location": "Praha 2120 00"
  },
  {
    "id": "6c3de5aa-58fb-43ba-9233-165e583781ac",
    "title": "iPhone 13 Pro 128GB, pěkný stav, 12 měsíců záruka",
    "price": "7 500 Kč",
    "link": "https://mobil.bazos.cz/inzerat/216120863/iphone-13-pro-128gb-pekny-stav-12-mesicu-zaruka.php",
    "date_posted": "- TOP - [14.3. 2026]",
    "brand": "Apple",
    "ad_type": "nabidka",
    "scraped_at": "2026-03-14T17:40:46.858Z",
    "description": "Prodám plně funkční iPhone ve výborném stavu. Prošel kontrolou a je připraven k okamžitému používání. Vše je možné před zakoupením vyzkoušet.\n\n- Záruka 12 měsíců\n- Odhlášený od iCloudu\n- Dostanete fakturu\n- Možnost osobního předání nebo zaslání pošto ...",
    "location": "Praha 2120 00"
  }
]